paramvalidator/__init__.py
paramvalidator/validator.py
paramvalidator/exceptions/__init__.py
paramvalidator/exceptions/count_validation_exception.py
paramvalidator/exceptions/kwarg_validation_exception.py
paramvalidator/exceptions/none_validation_exception.py
paramvalidator/exceptions/range_validation_exception.py
paramvalidator/exceptions/type_validation_exception.py
paramvalidator/exceptions/validation_exception.py
ai_param_validation-0.0.1.dist-info/LICENSE
ai_param_validation-0.0.1.dist-info/METADATA
ai_param_validation-0.0.1.dist-info/WHEEL
ai_param_validation-0.0.1.dist-info/top_level.txt
ai_param_validation-0.0.1.dist-info/RECORD
