Metadata-Version: 2.1
Name: ai-param-validation
Version: 0.0.1
Summary: A method parameter validation decorator
Home-page: https://github.com/pypa/sampleproject
Author: Dan Grecoe
Author-email: grecoe@microsoft.com
License: UNKNOWN
Project-URL: Bug Tracker, https://github.com/microsoft/ai-py-param-validation/issues
Platform: UNKNOWN
Classifier: Programming Language :: Python :: 3
Classifier: License :: OSI Approved :: MIT License
Classifier: Operating System :: OS Independent
Requires-Python: >=3.6
